school_grader/__init__.py
school_grader/equality.py
school_grader/html_test_result.py
school_grader/json_test_result.py
school_grader/test_case.py
school_grader-4.0.10.dist-info/METADATA
school_grader-4.0.10.dist-info/WHEEL
school_grader-4.0.10.dist-info/licenses/LICENSE
school_grader-4.0.10.dist-info/RECORD
