Metadata-Version: 2.1
Name: school_grader
Version: 4.0.10
Summary: Testing framework for Python students code.
Project-URL: Homepage, https://github.com/school-grader/school-grader
Project-URL: Bug Tracker, https://github.com/school-grader/school-grader/issues
Author-email: Marc-Olivier Derouin <marcolivier.derouin@poulet-frit.com>
License-File: LICENSE
Keywords: education,framework,python,python3,python3.10,python3.11,python3.7,python3.8,python3.9,school,students,test,testing
Classifier: License :: OSI Approved :: MIT License
Classifier: Operating System :: OS Independent
Classifier: Programming Language :: Python :: 3
Requires-Python: >=3.7
